README.txt
setup.py
xplhub.py
expel.apps.hub.egg-info/PKG-INFO
expel.apps.hub.egg-info/SOURCES.txt
expel.apps.hub.egg-info/dependency_links.txt
expel.apps.hub.egg-info/requires.txt
expel.apps.hub.egg-info/top_level.txt