Metadata-Version: 1.0
Name: expel.apps.hub
Version: 0.1
Summary: xPL Hub
Home-page: http://www.sffjunkie.co.uk/python-expel.html#hub
Author: Simon Kennedy
Author-email: code@sffjunkie.co.uk
License: Apache-2.0
Platform: UNKNOWN
